README
setup.py
anisble/__init__.py
anisble.egg-info/PKG-INFO
anisble.egg-info/SOURCES.txt
anisble.egg-info/dependency_links.txt
anisble.egg-info/requires.txt
anisble.egg-info/top_level.txt