Metadata-Version: 1.0
Name: anisble
Version: 0.1
Summary: You meant to type ansible. You ended up here. I don't want anybody being able to use this to hack you. So I made this.
Home-page: https://github.com/j00bar/anisble
Author: Joshua "jag" Ginsberg
Author-email: jag@flowtheory.net
License: UNKNOWN
Platform: UNKNOWN
